xs/__init__.py
xs/core/__global.py
xs/core/__init__.py
xs/core/autograd.py
xs/core/base.py
xs/layers/__init__.py
xs/layers/activators.py
xs/layers/base.py
xs/layers/convolutional.py
xs/layers/linear.py
xs/layers/normalize.py
xs/layers/ops.py
xs/layers/pooling.py
xs/nn/__init__.py
xs/nn/functional.py
xs/nn/grad_fn.py
xs/nn/initializers.py
xs/nn/models.py
xs/nn/objectives.py
xs/nn/rng.py
xs/nn/td_functional.py
xs/optim/__init__.py
xs/optim/adadelta.py
xs/optim/adagrad.py
xs/optim/adam.py
xs/optim/optimizer.py
xs/optim/rmsprop.py
xs/optim/sgd.py
xs/utils/__init__.py
xs/utils/common.py
xs/utils/toolkit.py
xs/utils/data/__init__.py
xs/utils/data/dataloader.py
xs/utils/data/dataset.py
xshinnosuke-0.1.8.dist-info/METADATA
xshinnosuke-0.1.8.dist-info/WHEEL
xshinnosuke-0.1.8.dist-info/top_level.txt
xshinnosuke-0.1.8.dist-info/RECORD
