Metadata-Version: 2.1
Name: xshinnosuke
Version: 0.1.8
Summary: Deep learning framework realized by Numpy purely, supports for both Dynamic Graph and Static Graph with GPU acceleration
Home-page: https://github.com/E1eveNn/xshinnosuke
Author: Eleven
Author-email: eleven_1111@outlook.com
License: UNKNOWN
Platform: UNKNOWN
Classifier: Programming Language :: Python :: 3
Classifier: License :: OSI Approved :: MIT License
Classifier: Operating System :: OS Independent
Requires-Python: >=3.6
